"security_poc2/__init__,py"
security_poc2/security_poc.py
security_poc2-500.0.0.dist-info/WHEEL
security_poc2-500.0.0.dist-info/METADATA
security_poc2-500.0.0.dist-info/RECORD
